{
	"$schema": "http://schema.management.azure.com/schemas/2015-01-01/deploymentTemplate.json#",
	"contentVersion": "1.0.0.0",
	"parameters": {
		"factoryName": {
			"type": "string",
			"metadata": "Data Factory name",
			"defaultValue": "chanleydf"
		}
	},
	"variables": {
		"factoryId": "[concat('Microsoft.DataFactory/factories/', parameters('factoryName'))]"
	},
	"resources": [
		{
			"name": "[concat(parameters('factoryName'), '/d_Personnel')]",
			"type": "Microsoft.DataFactory/factories/datasets",
			"apiVersion": "2018-06-01",
			"properties": {
				"linkedServiceName": {
					"referenceName": "chanleysvc",
					"type": "LinkedServiceReference"
				},
				"annotations": [],
				"type": "AzureSqlTable",
				"schema": [
					{
						"name": "LFBI_ID",
						"type": "int",
						"precision": 10
					},
					{
						"name": "LFBI_LoadTime",
						"type": "datetime2",
						"scale": 7
					},
					{
						"name": "LFBI_Start",
						"type": "datetime2",
						"scale": 7
					},
					{
						"name": "LFBI_End",
						"type": "datetime2",
						"scale": 7
					},
					{
						"name": "LFBI_Current",
						"type": "bit"
					},
					{
						"name": "billable",
						"type": "bit"
					},
					{
						"name": "active",
						"type": "bit"
					},
					{
						"name": "create_date",
						"type": "datetime",
						"precision": 23,
						"scale": 3
					},
					{
						"name": "user_id",
						"type": "int",
						"precision": 10
					},
					{
						"name": "first_name",
						"type": "varchar"
					},
					{
						"name": "last_name",
						"type": "varchar"
					},
					{
						"name": "FullName",
						"type": "varchar"
					},
					{
						"name": "login_id",
						"type": "varchar"
					},
					{
						"name": "email",
						"type": "varchar"
					},
					{
						"name": "bamboo_id",
						"type": "int",
						"precision": 10
					},
					{
						"name": "practice",
						"type": "varchar"
					},
					{
						"name": "current_manager",
						"type": "int",
						"precision": 10
					},
					{
						"name": "joblevel_rate",
						"type": "money",
						"precision": 19,
						"scale": 4
					},
					{
						"name": "Mobile_Phone",
						"type": "varchar"
					},
					{
						"name": "OnPTO",
						"type": "bit"
					},
					{
						"name": "xCustom",
						"type": "varchar"
					}
				],
				"typeProperties": {
					"schema": "DW",
					"table": "d_Personnel2"
				}
			},
			"dependsOn": []
		}
	]
}